main.py
nwb_tiff-0.1.0.dist-info/LICENSE
nwb_tiff-0.1.0.dist-info/METADATA
nwb_tiff-0.1.0.dist-info/WHEEL
nwb_tiff-0.1.0.dist-info/entry_points.txt
nwb_tiff-0.1.0.dist-info/top_level.txt
nwb_tiff-0.1.0.dist-info/RECORD
