Metadata-Version: 2.2
Name: nwb-tiff
Version: 0.1.0
Summary: Convert NWB files to TIFF format
Author: NileshArnaiya
License: CC0-1.0
Project-URL: Homepage, https://github.com/NileshArnaiya/NWB-TiFF-CONVERTOR
Requires-Python: >=3.6
License-File: LICENSE
